README.md
setup.py
nextcord/ext/pomice/__init__.py
nextcord/ext/pomice/enums.py
nextcord/ext/pomice/events.py
nextcord/ext/pomice/exceptions.py
nextcord/ext/pomice/filters.py
nextcord/ext/pomice/objects.py
nextcord/ext/pomice/player.py
nextcord/ext/pomice/pool.py
nextcord/ext/pomice/utils.py
nextcord_ext_pomice.egg-info/PKG-INFO
nextcord_ext_pomice.egg-info/SOURCES.txt
nextcord_ext_pomice.egg-info/dependency_links.txt
nextcord_ext_pomice.egg-info/requires.txt
nextcord_ext_pomice.egg-info/top_level.txt