Metadata-Version: 2.1
Name: nextcord-ext-pomice
Version: 1.1.7.1
Summary: The modern Lavalink wrapper designed for nextcord
Home-page: https://github.com/techpluscraft/nextcord-ext-pomice
Author: techpluscraft
License: GPL
Keywords: pomice,lavalink,nextcord
Platform: UNKNOWN
Classifier: Framework :: AsyncIO
Classifier: Operating System :: OS Independent
Classifier: Natural Language :: English
Classifier: Intended Audience :: Developers
Classifier: Programming Language :: Python :: 3 :: Only
Classifier: Programming Language :: Python :: 3.8
Classifier: Topic :: Software Development :: Libraries :: Python Modules
Classifier: Topic :: Software Development :: Libraries
Classifier: Topic :: Internet
Requires-Python: >=3.8
